LICENSE
MANIFEST.in
README.rst
requirements.txt
setup.cfg
setup.py
ttseries/__init__.py
ttseries/exceptions.py
ttseries/serializers.py
ttseries/utils.py
ttseries.egg-info/PKG-INFO
ttseries.egg-info/SOURCES.txt
ttseries.egg-info/dependency_links.txt
ttseries.egg-info/not-zip-safe
ttseries.egg-info/requires.txt
ttseries.egg-info/top_level.txt
ttseries/ts/__init__.py
ttseries/ts/base.py
ttseries/ts/hash.py
ttseries/ts/numpy.py
ttseries/ts/pandas.py
ttseries/ts/sample.py