Metadata-Version: 1.2
Name: ttseries
Version: 0.2.2
Summary: Time series data store in Redis
Home-page: https://github.com/nooperpudd/ttseries
Author: Winton Wang
Author-email: 365504029@qq.com
License: LGPLv3
Keywords: Time Series,Redis Time Series
Platform: any
Classifier: Development Status :: 5 - Production/Stable
Classifier: Intended Audience :: Developers
Classifier: License :: OSI Approved
Classifier: License :: OSI Approved :: GNU Lesser General Public License v3 (LGPLv3)
Classifier: Programming Language :: Python
Classifier: Programming Language :: Python :: 3
Classifier: Programming Language :: Python :: 3 :: Only
Classifier: Programming Language :: Python :: 3.6
Classifier: Programming Language :: Python :: 3.7
Classifier: Programming Language :: Python :: 3.8
Classifier: Topic :: Software Development
Classifier: Topic :: Software Development :: Libraries
Requires-Python: >=3.6
